{
  "version": "5",
  "dialect": "pg",
  "id": "07eb7ea2-1f23-43d6-a1b9-7784b1059125",
  "prevId": "f3615457-2962-4fc6-992c-eaa3bf51977e",
  "tables": {
    "info": {
      "name": "info",
      "schema": "",
      "columns": {
        "id": {
          "name": "id",
          "type": "serial",
          "primaryKey": true,
          "notNull": true
        },
        "name": {
          "name": "name",
          "type": "text",
          "primaryKey": false,
          "notNull": false
        },
        "description": {
          "name": "description",
          "type": "text",
          "primaryKey": false,
          "notNull": false
        }
      },
      "indexes": {},
      "foreignKeys": {},
      "compositePrimaryKeys": {}
    },
    "transaction": {
      "name": "transaction",
      "schema": "",
      "columns": {
        "id": {
          "name": "id",
          "type": "serial",
          "primaryKey": true,
          "notNull": true
        },
        "sender_user_id": {
          "name": "sender_user_id",
          "type": "integer",
          "primaryKey": false,
          "notNull": false
        },
        "recipient_user_id": {
          "name": "recipient_user_id",
          "type": "integer",
          "primaryKey": false,
          "notNull": false
        }
      },
      "indexes": {},
      "foreignKeys": {
        "transaction_sender_user_id_info_id_fk": {
          "name": "transaction_sender_user_id_info_id_fk",
          "tableFrom": "transaction",
          "tableTo": "info",
          "columnsFrom": [
            "sender_user_id"
          ],
          "columnsTo": [
            "id"
          ],
          "onDelete": "no action",
          "onUpdate": "no action"
        },
        "transaction_recipient_user_id_info_id_fk": {
          "name": "transaction_recipient_user_id_info_id_fk",
          "tableFrom": "transaction",
          "tableTo": "info",
          "columnsFrom": [
            "recipient_user_id"
          ],
          "columnsTo": [
            "id"
          ],
          "onDelete": "no action",
          "onUpdate": "no action"
        }
      },
      "compositePrimaryKeys": {}
    }
  },
  "enums": {},
  "schemas": {},
  "_meta": {
    "schemas": {},
    "tables": {},
    "columns": {}
  }
}